{
	"pools": [
		{
			"rolls": 1,
			"entries": [
				{
					"type": "minecraft:item",
					"name": "minecraft:beehive",
					"functions": [
						{
							"function": "minecraft:set_nbt",
							"tag": "{CustomModelData: 456002, display: {Name: '{\"text\":\"Milky Way DHD\", \"italic\": false}', Lore:['{\"text\":\"Place near a stargate to control the gate\"}']}, BlockEntityTag: {Bees: [{EntityData:{id:\"minecraft:marker\",Tags:[\"custom_block\",\"sg.milky_way_dhd\"]}}]}}"
						}
					]
				}
			]
		}
	]
}
